orvixengine/__init__.py
orvixengine/animation.py
orvixengine/asset_manager.py
orvixengine/camera.py
orvixengine/config_manager.py
orvixengine/engine.py
orvixengine/event_manager (2).py
orvixengine/event_manager.py
orvixengine/game_object.py
orvixengine/game_objet.py
orvixengine/input_manager.py
orvixengine/logger.py
orvixengine/physics_manager.py
orvixengine/scene.py
orvixengine/sound_manager.py
orvixengine/ui_manager.py
orvixengine-1.1.0.dist-info/METADATA
orvixengine-1.1.0.dist-info/WHEEL
orvixengine-1.1.0.dist-info/top_level.txt
orvixengine-1.1.0.dist-info/RECORD
