Metadata-Version: 2.4
Name: OrvixEngine
Version: 1.1.0
Summary: OrvixEngine: The modular 2D Game Engine SDK built on Pygame for rapid development.
Author: ORVIX GAMES
Author-email: help@orvixgames.com
Maintainer: ORVIX GAMES Geliştirme Ekibi
License: MIT
Project-URL: Homepage, https://orvixgames.com/modul/orvix-engine-sdk/
Project-URL: Documentation, https://orvixgames.com/modul/orvix-engine-sdk/docs
Project-URL: Issue Tracker, https://orvixgames.com/support/issues
Project-URL: Support, https://orvixgames.com/support
Project-URL: Source Code, https://orvixgames.com/modul/orvix-engine-sdk/source
Keywords: game-engine 2d pygame platformer physics sdk modular framework
Classifier: Development Status :: 4 - Beta
Classifier: Intended Audience :: Developers
Classifier: Intended Audience :: Education
Classifier: Topic :: Software Development :: Libraries
Classifier: Topic :: Games/Entertainment
Classifier: Topic :: Games/Entertainment :: Arcade
Classifier: License :: OSI Approved :: MIT License
Classifier: Programming Language :: Python :: 3
Classifier: Programming Language :: Python :: 3.8
Classifier: Programming Language :: Python :: 3.9
Classifier: Programming Language :: Python :: 3.10
Classifier: Programming Language :: Python :: 3.11
Classifier: Programming Language :: Python :: 3.12
Requires-Dist: pygame>=2.0.0
Dynamic: author
Dynamic: author-email
Dynamic: classifier
Dynamic: description
Dynamic: description-content-type
Dynamic: keywords
Dynamic: license
Dynamic: maintainer
Dynamic: project-url
Dynamic: requires-dist
Dynamic: summary
